modular_client/__init__.py
modular_client/modular_client.py
modular_client-8.4.3.dist-info/LICENSE
modular_client-8.4.3.dist-info/METADATA
modular_client-8.4.3.dist-info/WHEEL
modular_client-8.4.3.dist-info/top_level.txt
modular_client-8.4.3.dist-info/RECORD
