Metadata-Version: 2.1
Name: modular-client
Version: 8.4.3
Summary: Modular device Python client interface for communicating with and calling remote methods on modular device servers.
Home-page: https://github.com/janelia-pypi/modular_client_python
Author: Peter Polidoro
Author-email: peter@polidoro.io
License: BSD
Keywords: modular serial arduino device client modulardevice modular-device modular_device modularclient modular-client modular_client json json-rpc
Platform: UNKNOWN
Classifier: Development Status :: 5 - Production/Stable
Classifier: Intended Audience :: Developers
Classifier: Topic :: Software Development :: Build Tools
Classifier: License :: OSI Approved :: BSD License
Classifier: Programming Language :: Python :: 3
License-File: LICENSE
Requires-Dist: serial-interface
Requires-Dist: inflection
Requires-Dist: sre-yield
